synclane/__init__.py
synclane/_base.py
synclane/_export.py
synclane/ts/base.ts
synclane-0.6.1.dist-info/METADATA
synclane-0.6.1.dist-info/WHEEL
synclane-0.6.1.dist-info/licenses/LICENSE.txt
synclane-0.6.1.dist-info/RECORD
